microgrids/__init__.py
microgrids/components.py
microgrids/economics.py
microgrids/operation.py
microgrids/plotting.py
microgrids-0.3.1.dist-info/METADATA
microgrids-0.3.1.dist-info/WHEEL
microgrids-0.3.1.dist-info/licenses/LICENSE.md
microgrids-0.3.1.dist-info/RECORD
