Metadata-Version: 2.1
Name: microgrids
Version: 0.3.1
Summary: Operational & economic simulation of Microgrid projects
Project-URL: Homepage, https://github.com/Microgrids-X/Microgrids.py
Project-URL: Bug Tracker, https://github.com/Microgrids-X/Microgrids.py/issues
Author-email: Pierre <pierre.haessig@centralesupelec.fr>
Maintainer-email: Pierre <pierre.haessig@centralesupelec.fr>
License: MIT License
License-File: LICENSE.md
Classifier: License :: OSI Approved :: MIT License
Classifier: Operating System :: OS Independent
Classifier: Programming Language :: Python :: 3
Requires-Python: >=3.10
Requires-Dist: matplotlib
Requires-Dist: numpy
